beetle/__init__.py
beetle/__main__.py
beetle/_aws.py
beetle/_gpg.py
beetle/_server.py
beetle/_state.py
beetle/cmdline.py
beetle/resources.py
beetle/translate.py
beetle/upload.py
beetle/_defaults/requirements/arch.txt
beetle/_defaults/requirements/base.txt
beetle/_defaults/requirements/fedora.txt
beetle/_defaults/requirements/linux.txt
beetle/_defaults/requirements/ubuntu.txt
beetle/_defaults/src/build/docker/arch/.bashrc
beetle/_defaults/src/build/docker/arch/Dockerfile
beetle/_defaults/src/build/docker/arch/gpg-agent.conf
beetle/_defaults/src/build/docker/arch/motd
beetle/_defaults/src/build/docker/fedora/.bashrc
beetle/_defaults/src/build/docker/fedora/.rpmmacros
beetle/_defaults/src/build/docker/fedora/Dockerfile
beetle/_defaults/src/build/docker/fedora/gpg-agent.conf
beetle/_defaults/src/build/docker/fedora/motd
beetle/_defaults/src/build/docker/ubuntu/.bashrc
beetle/_defaults/src/build/docker/ubuntu/Dockerfile
beetle/_defaults/src/build/docker/ubuntu/gpg-agent.conf
beetle/_defaults/src/build/docker/ubuntu/gpg.conf
beetle/_defaults/src/build/docker/ubuntu/motd
beetle/_defaults/src/build/settings/arch.json
beetle/_defaults/src/build/settings/base.json
beetle/_defaults/src/build/settings/fedora.json
beetle/_defaults/src/build/settings/linux.json
beetle/_defaults/src/build/settings/mac.json
beetle/_defaults/src/build/settings/release.json
beetle/_defaults/src/build/settings/ubuntu.json
beetle/_defaults/src/build/settings/windows.json
beetle/_defaults/src/freeze/mac/Contents/Info.plist
beetle/_defaults/src/freeze/windows/version_info.py
beetle/_defaults/src/installer/linux/usr/share/applications/AppName.desktop
beetle/_defaults/src/installer/windows/Installer.nsi
beetle/_defaults/src/repo/fedora/AppName.repo
beetle/_defaults/src/repo/ubuntu/distributions
beetle/builtin_commands/__init__.py
beetle/builtin_commands/_account.py
beetle/builtin_commands/_docker.py
beetle/builtin_commands/_licensing.py
beetle/builtin_commands/_template.py
beetle/builtin_commands/_util.py
qbeetle-0.0.4.dist-info/licenses/LICENSE
qbeetle-0.0.4.dist-info/METADATA
qbeetle-0.0.4.dist-info/WHEEL
qbeetle-0.0.4.dist-info/entry_points.txt
qbeetle-0.0.4.dist-info/top_level.txt
qbeetle-0.0.4.dist-info/RECORD
