Metadata-Version: 2.4
Name: qbeetle
Version: 0.0.4
Summary: Create cross-platform desktop applications with Python and Qt
Home-page: https://beetle-tool.github.io/beetle-doc/
Author: Danqing Li
Author-email: 492847382@qq.com
Keywords: PyQt5 PyQt6 PySide2 PySide6
Platform: MacOS
Platform: Windows
Platform: Debian
Platform: Fedora
Platform: CentOS
Platform: Arch
Classifier: Development Status :: 5 - Production/Stable
Classifier: Intended Audience :: Developers
Classifier: License :: OSI Approved :: MIT License
Classifier: Operating System :: OS Independent
Classifier: Programming Language :: Python
Classifier: Programming Language :: Python :: 3
Classifier: Topic :: Software Development :: Libraries
Classifier: Topic :: Software Development :: Libraries :: Python Modules
Requires-Python: >=3.8
License-File: LICENSE
Requires-Dist: Nuitka>=1.8
Requires-Dist: GitPython
Requires-Dist: Babel
Requires-Dist: QtPy
Provides-Extra: licensing
Requires-Dist: rsa>=3.4.2; extra == "licensing"
Provides-Extra: sentry
Requires-Dist: sentry-sdk>=0.6.6; extra == "sentry"
Provides-Extra: upload
Requires-Dist: boto3; extra == "upload"
Dynamic: author
Dynamic: author-email
Dynamic: classifier
Dynamic: description
Dynamic: description-content-type
Dynamic: home-page
Dynamic: keywords
Dynamic: license-file
Dynamic: platform
Dynamic: provides-extra
Dynamic: requires-dist
Dynamic: requires-python
Dynamic: summary
